README.md
setup.cfg
setup.py
compoda/__init__.py
compoda/core.py
compoda/utils.py
compoda.egg-info/PKG-INFO
compoda.egg-info/SOURCES.txt
compoda.egg-info/dependency_links.txt
compoda.egg-info/not-zip-safe
compoda.egg-info/requires.txt
compoda.egg-info/top_level.txt