Metadata-Version: 1.1
Name: compoda
Version: 0.3.5
Summary: Compositional data analysis tools implemented in Python.
Home-page: https://github.com/ofgulban/compoda
Author: Omer Faruk Gulban
Author-email: faruk.gulban@maastrichtuniversity.nl
License: BSD-3-clause
Download-URL: https://github.com/ofgulban/compoda/archive/0.3.5.tar.gz
Platform: UNKNOWN
